validate_rg/__init__.py
validate_rg/__main__.py
validate_rg/cli.py
validate_rg/py.typed
validate_rg/validate_rg.py
validate_rg-0.0.1.dist-info/LICENSE
validate_rg-0.0.1.dist-info/WHEEL
validate_rg-0.0.1.dist-info/METADATA
validate_rg-0.0.1.dist-info/RECORD
