Metadata-Version: 2.1
Name: validate-rg
Version: 0.0.1
Summary: Faz a validação de RG (SSP SP) Brasileiro
Home-page: https://github.com/drummerzzz/pypi_validate_rg/README.md
License: MIT
Keywords: rg,validador,validação,validation,validator,poetry
Author: Drummerzzz
Author-email: devdrummerzzz@gmail.com
Requires-Python: >=3.8,<4.0
Classifier: License :: OSI Approved :: MIT License
Classifier: Programming Language :: Python :: 3
Classifier: Programming Language :: Python :: 3.8
Classifier: Programming Language :: Python :: 3.9
Project-URL: Repository, https://github.com/drummerzzz/pypi_validate_rg
